indxr/__init__.py
indxr/indxr.py
indxr/handlers/__init__.py
indxr/handlers/csv_handler.py
indxr/handlers/custom_handler.py
indxr/handlers/jsonl_handler.py
indxr/handlers/multi_vector_handler.py
indxr/handlers/numpy_handler.py
indxr/handlers/txt_handler.py
indxr-0.1.6.dist-info/LICENSE
indxr-0.1.6.dist-info/METADATA
indxr-0.1.6.dist-info/WHEEL
indxr-0.1.6.dist-info/top_level.txt
indxr-0.1.6.dist-info/RECORD
