Metadata-Version: 2.1
Name: indxr
Version: 0.1.6
Summary: indxr: A Python utility for indexing long files.
Home-page: https://github.com/AmenRa/indxr
Author: Elias Bassani
Author-email: elias.bssn@gmail.com
Keywords: text index,file index,index,indexer,indexing,information retrieval,natural language processing
Classifier: Programming Language :: Python :: 3
Classifier: License :: OSI Approved :: MIT License
Classifier: Intended Audience :: Science/Research
Classifier: Operating System :: OS Independent
Classifier: Topic :: Text Processing :: General
Requires-Python: >=3.10
License-File: LICENSE
Requires-Dist: numpy
Requires-Dist: orjson
